py_fgui/__init__.py
py_fgui/fairy_gui.py
py_fgui-0.0.2.dist-info/LICENSE
py_fgui-0.0.2.dist-info/METADATA
py_fgui-0.0.2.dist-info/WHEEL
py_fgui-0.0.2.dist-info/top_level.txt
py_fgui-0.0.2.dist-info/RECORD
