Metadata-Version: 2.1
Name: py-fgui
Version: 0.0.2
Summary: A python package for parsing FGUI project files
Home-page: https://github.com/MisakaCirno/py_fgui
Author: MisakaCirno
Author-email: misakacirno@qq.com
Classifier: Programming Language :: Python :: 3
Classifier: License :: OSI Approved :: MIT License
Classifier: Operating System :: OS Independent
Requires-Python: >=3.6
License-File: LICENSE
